magplan/__init__.py
magplan/admin.py
magplan/apps.py
magplan/context_processors.py
magplan/dynamic_preferences_registry.py
magplan/forms.py
magplan/middleware.py
magplan/models.py
magplan/registries.py
magplan/urls.py
magplan/utils.py
magplan/conf/__init__.py
magplan/conf/settings.py
magplan/integrations/__init__.py
magplan/integrations/images.py
magplan/integrations/posts.py
magplan/locale/en/LC_MESSAGES/django.mo
magplan/locale/en/LC_MESSAGES/django.po
magplan/locale/ru/LC_MESSAGES/django.mo
magplan/locale/ru/LC_MESSAGES/django.po
magplan/management/__init__.py
magplan/management/commands/__init__.py
magplan/management/commands/render.py
magplan/migrations/0001_initial.py
magplan/migrations/0002_auto_20201115_1140.py
magplan/migrations/0003_auto_20201121_1750.py
magplan/migrations/0004_post_features.py
magplan/migrations/0005_auto_20210213_1556.py
magplan/migrations/0006_auto_20210316_1840.py
magplan/migrations/0007_auto_20210316_1900.py
magplan/migrations/0008_auto_20210318_0108.py
magplan/migrations/0009_auto_20210523_1641.py
magplan/migrations/0010_auto_20210624_1041.py
magplan/migrations/0011_auto_20210624_1817.py
magplan/migrations/0012_alter_attachment_meta_alter_comment_meta_and_more.py
magplan/migrations/0013_sitepreferencemodel.py
magplan/migrations/__init__.py
magplan/tasks/__init__.py
magplan/tasks/send_idea_comment_notification.py
magplan/tasks/send_idea_notification.py
magplan/tasks/send_post_comment_notification.py
magplan/tasks/upload_post_to_wp.py
magplan/tasks/utils.py
magplan/templates/__init__.py
magplan/templates/_test_issues.py
magplan/templates/layout_plan.html
magplan/templates/email/_vote_from_email.html
magplan/templates/email/assigned_to_you.html
magplan/templates/email/idea_approved.html
magplan/templates/email/new_comment.html
magplan/templates/email/new_idea.html
magplan/templates/magplan/articles/advert.html
magplan/templates/magplan/articles/archived.html
magplan/templates/magplan/articles/default.html
magplan-3.6.1.dist-info/METADATA
magplan-3.6.1.dist-info/WHEEL
magplan-3.6.1.dist-info/top_level.txt
magplan-3.6.1.dist-info/RECORD
