Metadata-Version: 2.4
Name: magplan
Version: 3.6.1
Author-email: Ilya Rusanen <ilya@rusanen.co.uk>
Requires-Python: >=3.9
Requires-Dist: boto3>=1.34.0
Requires-Dist: celery[redis]>=5.3.6
Requires-Dist: django-ace>=1.32.0
Requires-Dist: django-admin-list-filter-dropdown>=1.0.3
Requires-Dist: django-dynamic-preferences>=1.16.0
Requires-Dist: django-filter>=23.5
Requires-Dist: django-picklefield>=3.1
Requires-Dist: django-polymorphic>=3.1.0
Requires-Dist: django-widget-tweaks>=1.5.0
Requires-Dist: django>=4
Requires-Dist: html2text>=2020.1.16
Requires-Dist: mistune==0.8.4
Requires-Dist: pymysql>=1.1.0
Requires-Dist: python-slugify>=8.0.1
Requires-Dist: requests>=2.31.0
Requires-Dist: sshtunnel>=0.4.0
Requires-Dist: psycopg>=3.1.8
